<annotation>
	<folder></folder>
	<filename>rgb_62_png.rf.b52ecaeb52b8ac95f69c46f643ce4b18.jpg</filename>
	<path>rgb_62_png.rf.b52ecaeb52b8ac95f69c46f643ce4b18.jpg</path>
	<source>
		<database>roboflow.ai</database>
	</source>
	<size>
		<width>640</width>
		<height>640</height>
		<depth>3</depth>
	</size>
	<segmented>0</segmented>
	<object>
		<name>handle_knife</name>
		<pose>Unspecified</pose>
		<truncated>0</truncated>
		<difficult>0</difficult>
		<occluded>0</occluded>
		<bndbox>
			<xmin>163</xmin>
			<xmax>245</xmax>
			<ymin>445</ymin>
			<ymax>568</ymax>
		</bndbox>
	</object>
</annotation>
