<annotation>
	<folder></folder>
	<filename>rgb_143_png.rf.0edb7e2744991519ebf16734501b0b0a.jpg</filename>
	<path>rgb_143_png.rf.0edb7e2744991519ebf16734501b0b0a.jpg</path>
	<source>
		<database>roboflow.ai</database>
	</source>
	<size>
		<width>640</width>
		<height>640</height>
		<depth>3</depth>
	</size>
	<segmented>0</segmented>
	<object>
		<name>top_folk</name>
		<pose>Unspecified</pose>
		<truncated>0</truncated>
		<difficult>0</difficult>
		<occluded>0</occluded>
		<bndbox>
			<xmin>310</xmin>
			<xmax>385</xmax>
			<ymin>354</ymin>
			<ymax>402</ymax>
		</bndbox>
	</object>
</annotation>
